README
setup.py
namespacetrie/__init__.py
namespacetrie/nstrie.py
namespacetrie.egg-info/PKG-INFO
namespacetrie.egg-info/SOURCES.txt
namespacetrie.egg-info/dependency_links.txt
namespacetrie.egg-info/requires.txt
namespacetrie.egg-info/top_level.txt
tests/__init__.py
tests/nstrie_test.py