Metadata-Version: 1.0
Name: namespacetrie
Version: 0.1
Summary: A Trie implementation that manages not the single characters but treats its values as typical namespaces.
Home-page: https://github.com/knutwalker/namespacetrie
Author: Paul Horn
Author-email: knutwalker@gmail.com
License: GPLv3
Keywords: namespace trie
Platform: UNKNOWN
